LICENSE
MANIFEST.in
README.md
requirements.txt
setup.cfg
setup.py
cartoview/__init__.py
cartoview/apps.py
cartoview/asgi.py
cartoview/celery_app.py
cartoview/context_processors.py
cartoview/fields.py
cartoview/log_handler.py
cartoview/routing.py
cartoview/urls.py
cartoview/views.py
cartoview/wsgi.py
cartoview/api/__init__.py
cartoview/api/admin.py
cartoview/api/apps.py
cartoview/api/fields.py
cartoview/api/filters.py
cartoview/api/models.py
cartoview/api/permissions.py
cartoview/api/tests.py
cartoview/api/urls.py
cartoview/api/migrations/__init__.py
cartoview/api/serializers/__init__.py
cartoview/api/serializers/app_manager.py
cartoview/api/serializers/base_resource.py
cartoview/api/serializers/connections.py
cartoview/api/serializers/layers.py
cartoview/api/serializers/maps.py
cartoview/api/serializers/user.py
cartoview/api/views/__init__.py
cartoview/api/views/app_manager.py
cartoview/api/views/connections.py
cartoview/api/views/layers.py
cartoview/api/views/maps.py
cartoview/api/views/users.py
cartoview/app_manager/__init__.py
cartoview/app_manager/admin.py
cartoview/app_manager/admin_urls.py
cartoview/app_manager/apps.py
cartoview/app_manager/apps_operations.py
cartoview/app_manager/config.py
cartoview/app_manager/decorators.py
cartoview/app_manager/exceptions.py
cartoview/app_manager/installer.py
cartoview/app_manager/models.py
cartoview/app_manager/os_utils.py
cartoview/app_manager/req_installer.py
cartoview/app_manager/serializers.py
cartoview/app_manager/tests.py
cartoview/app_manager/urls.py
cartoview/app_manager/views.py
cartoview/app_manager/wagtail_hooks.py
cartoview/app_manager/fixtures/app_stores.json
cartoview/app_manager/management/__init__.py
cartoview/app_manager/management/commands/__init__.py
cartoview/app_manager/management/commands/install_app.py
cartoview/app_manager/management/commands/load_current_apps.py
cartoview/app_manager/management/commands/update_current_apps.py
cartoview/app_manager/migrations/0001_initial.py
cartoview_2.egg-info/PKG-INFO
cartoview_2.egg-info/SOURCES.txt
cartoview_2.egg-info/dependency_links.txt
cartoview_2.egg-info/requires.txt
cartoview_2.egg-info/top_level.txt