Metadata-Version: 2.1
Name: cartoview-2
Version: 0.2a15
Summary: A GIS Web Mapping Application Market. Create, share, and visualize GIS Web Mapping Applications
Home-page: https://github.com/cartologic/cartoview_2/
Author: cartologic
Author-email: cartoview@cartologic.com
License: BSD
Keywords: cartoview,gis,django,web mapping,geonode,application management
Platform: UNKNOWN
Classifier: Development Status :: 4 - Beta
Classifier: Environment :: Web Environment
Classifier: Framework :: Django :: 2.2
Classifier: Intended Audience :: Developers
Classifier: License :: OSI Approved :: BSD License
Classifier: Operating System :: OS Independent
Classifier: Programming Language :: Python
Classifier: Programming Language :: Python :: 3.6
Classifier: Programming Language :: Python :: 3.7
Classifier: Programming Language :: Python :: 3.8
Classifier: Topic :: Internet :: WWW/HTTP
Classifier: Topic :: Internet :: WWW/HTTP :: Dynamic Content
Classifier: Topic :: Internet :: WWW/HTTP :: Dynamic Content :: Content Management System
Classifier: Topic :: Scientific/Engineering
Classifier: Topic :: Scientific/Engineering :: GIS
Classifier: Topic :: Software Development
Provides-Extra: testing
Provides-Extra: docs
